pypff.cpython-310-darwin.so
libpff_python-20231205.dist-info/METADATA
libpff_python-20231205.dist-info/WHEEL
libpff_python-20231205.dist-info/top_level.txt
libpff_python-20231205.dist-info/RECORD
