Metadata-Version: 2.1
Name: libpff-python
Version: 20231205
Summary: Python bindings module for libpff
Author: Joachim Metz
Author-email: joachim.metz@gmail.com
License: GNU Lesser General Public License v3 or later (LGPLv3+)
Classifier: Development Status :: 3 - Alpha
Classifier: Programming Language :: Python
Requires-Python: >=3.7
